spockflow/__init__.py
spockflow/_imports.py
spockflow/_serializable.py
spockflow/_util.py
spockflow/_version.py
spockflow/config_node.py
spockflow/core.py
spockflow/exceptions.py
spockflow/nodes.py
spockflow/components/__init__.py
spockflow/components/calculate.py
spockflow/components/dtable.py
spockflow/components/todo_inputs.py
spockflow/components/scorecard/__init__.py
spockflow/components/scorecard/exceptions.py
spockflow/components/scorecard/logger.py
spockflow/components/scorecard/probability.py
spockflow/components/scorecard/v2/__init__.py
spockflow/components/scorecard/v2/adjustments.py
spockflow/components/scorecard/v2/common.py
spockflow/components/scorecard/v2/criteria.py
spockflow/components/scorecard/v2/criteria_categorical.py
spockflow/components/scorecard/v2/criteria_numerical.py
spockflow/components/scorecard/v2/scorecard.py
spockflow/components/scorecard/v2/ui.py
spockflow/components/tree/__init__.py
spockflow/components/tree/exceptions.py
spockflow/components/tree/settings.py
spockflow/components/tree/v1/__init__.py
spockflow/components/tree/v1/compiled.py
spockflow/components/tree/v1/core.py
spockflow/components/treelite/__init__.py
spockflow/components/treelite/core.py
spockflow/inference/__init__.py
spockflow/inference/cache.py
spockflow/inference/exceptions.py
spockflow/inference/handler.py
spockflow/inference/model_loader.py
spockflow/inference/settings.py
spockflow/inference/util.py
spockflow/inference/config/__init__.py
spockflow/inference/config/loader/__init__.py
spockflow/inference/config/loader/base.py
spockflow/inference/config/loader/empty.py
spockflow/inference/config/loader/yamlmanager.py
spockflow/inference/io/__init__.py
spockflow/inference/io/accept_type_parser.py
spockflow/inference/io/content_types.py
spockflow/inference/io/decoders.py
spockflow/inference/io/encoders.py
spockflow/inference/io/json_encoder.py
spockflow/inference/io/responses.py
spockflow/inference/server/__init__.py
spockflow/inference/server/asgi.py
spockflow-0.3.0.post1.dist-info/licenses/LICENSE
spockflow-0.3.0.post1.dist-info/METADATA
spockflow-0.3.0.post1.dist-info/WHEEL
spockflow-0.3.0.post1.dist-info/top_level.txt
spockflow-0.3.0.post1.dist-info/RECORD
