Metadata-Version: 2.4
Name: SpockFlow
Version: 0.3.0.post1
Summary: Everything you could ever dream of
Author-email: Sholto Armstrong <sjnarmstrong@gmail.com>
License: MIT License
Classifier: Development Status :: 2 - Pre-Alpha
Classifier: Intended Audience :: Developers
Classifier: Natural Language :: English
Classifier: Programming Language :: Python :: 3
Classifier: Programming Language :: Python :: 3.12
Classifier: Programming Language :: Python :: 3.11
Classifier: Programming Language :: Python :: 3.10
Classifier: Programming Language :: Python :: 3.9
Classifier: Programming Language :: Python :: 3.8
Classifier: Topic :: Software Development :: Libraries :: Application Frameworks
Requires-Python: >=3.8
License-File: LICENSE
Requires-Dist: sf-hamilton>=1.56.0
Requires-Dist: pydantic>=2.5.2
Requires-Dist: pydantic_settings>=2.2.1
Requires-Dist: cachetools>=5.3.3
Requires-Dist: treelite>=4.2.0
Provides-Extra: dev
Requires-Dist: build; extra == "dev"
Requires-Dist: coverage[toml]; extra == "dev"
Requires-Dist: pytest; extra == "dev"
Requires-Dist: pytest-cov; extra == "dev"
Requires-Dist: black; extra == "dev"
Requires-Dist: versioneer; extra == "dev"
Provides-Extra: parsers
Requires-Dist: jsonpath-ng==1.6.0; extra == "parsers"
Provides-Extra: webapp
Requires-Dist: fastapi>=0.104.1; extra == "webapp"
Requires-Dist: uvicorn>=0.24.0.post1; extra == "webapp"
Requires-Dist: gunicorn>=21.2.0; extra == "webapp"
Provides-Extra: yaml
Requires-Dist: PyYAML>=5.0; extra == "yaml"
Dynamic: license-file
